build_tools/changelog.py
docs/source/conf.py
extension_templates/distributions.py
extension_templates/regression.py
extension_templates/survival.py
skpro/__init__.py
skpro/base/__init__.py
skpro/base/_base.py
skpro/benchmarking/__init__.py
skpro/benchmarking/evaluate.py
skpro/benchmarking/tests/__init__.py
skpro/benchmarking/tests/test_evaluate.py
skpro/datatypes/__init__.py
skpro/datatypes/_check.py
skpro/datatypes/_common.py
skpro/datatypes/_convert.py
skpro/datatypes/_examples.py
skpro/datatypes/_registry.py
skpro/datatypes/_adapter/__init__.py
skpro/datatypes/_adapter/polars.py
skpro/datatypes/_base/__init__.py
skpro/datatypes/_base/_base.py
skpro/datatypes/_convert_utils/__init__.py
skpro/datatypes/_convert_utils/_coerce.py
skpro/datatypes/_convert_utils/_convert.py
skpro/datatypes/_proba/__init__.py
skpro/datatypes/_proba/_check.py
skpro/datatypes/_proba/_convert.py
skpro/datatypes/_proba/_examples.py
skpro/datatypes/_proba/_registry.py
skpro/datatypes/_table/__init__.py
skpro/datatypes/_table/_base.py
skpro/datatypes/_table/_check.py
skpro/datatypes/_table/_convert.py
skpro/datatypes/_table/_examples.py
skpro/datatypes/_table/_registry.py
skpro/datatypes/tests/__init__.py
skpro/datatypes/tests/test_check.py
skpro/datatypes/tests/test_convert.py
skpro/datatypes/tests/test_convert_to.py
skpro/datatypes/tests/test_lookup.py
skpro/datatypes/tests/test_polars.py
skpro/distributions/__init__.py
skpro/distributions/alpha.py
skpro/distributions/beta.py
skpro/distributions/binomial.py
skpro/distributions/chi_squared.py
skpro/distributions/delta.py
skpro/distributions/empirical.py
skpro/distributions/erlang.py
skpro/distributions/exponential.py
skpro/distributions/fisk.py
skpro/distributions/gamma.py
skpro/distributions/geometric.py
skpro/distributions/halfcauchy.py
skpro/distributions/halflogistic.py
skpro/distributions/halfnormal.py
skpro/distributions/histogram.py
skpro/distributions/hurdle.py
skpro/distributions/inversegamma.py
skpro-2.11.0.dist-info/licenses/AUTHORS.rst
skpro-2.11.0.dist-info/licenses/LICENSE.txt
skpro-2.11.0.dist-info/METADATA
skpro-2.11.0.dist-info/WHEEL
skpro-2.11.0.dist-info/top_level.txt
skpro-2.11.0.dist-info/zip-safe
skpro-2.11.0.dist-info/RECORD
