Metadata-Version: 2.4
Name: skpro
Version: 2.11.0
Summary: A unified framework for tabular probabilistic regression, time-to-event prediction, and probability distributions in python
Author: Franz Király, Frithjof Gressmann, Vitaly Davydov
Author-email: skpro developers <info@sktime.net>
Maintainer-email: skpro developers <info@sktime.net>
Project-URL: Homepage, https://github.com/sktime/skpro
Project-URL: Repository, https://github.com/sktime/skpro
Project-URL: Documentation, https://github.com/sktime/skpro
Project-URL: Download, https://pypi.org/project/skpro/#files
Project-URL: API Reference, https://github.com/sktime/skpro
Project-URL: Release Notes, https://github.com/sktime/skpro
Keywords: data-science,machine-learning,data-mining,time-series,scikit-learn,regression
Classifier: Intended Audience :: Science/Research
Classifier: Intended Audience :: Developers
Classifier: License :: OSI Approved :: BSD License
Classifier: Programming Language :: Python
Classifier: Topic :: Software Development
Classifier: Topic :: Scientific/Engineering
Classifier: Operating System :: Microsoft :: Windows
Classifier: Operating System :: POSIX
Classifier: Operating System :: Unix
Classifier: Operating System :: MacOS
Classifier: Programming Language :: Python :: 3.10
Classifier: Programming Language :: Python :: 3.11
Classifier: Programming Language :: Python :: 3.12
Classifier: Programming Language :: Python :: 3.13
Classifier: Programming Language :: Python :: 3.14
Requires-Python: <3.15,>=3.9
License-File: LICENSE.txt
License-File: AUTHORS.rst
Requires-Dist: numpy<2.4,>=1.21.0
Requires-Dist: pandas<2.4.0,>=1.1.0
Requires-Dist: packaging
Requires-Dist: scikit-base<0.14.0,>=0.6.1
Requires-Dist: scikit-learn<1.8.0,>=0.24.0
Requires-Dist: scipy<2.0.0,>=1.2.0
Provides-Extra: all-extras
Requires-Dist: distfit; python_version < "3.13" and extra == "all-extras"
Requires-Dist: lifelines<0.31.0; python_version < "3.13" and extra == "all-extras"
Requires-Dist: mapie; python_version < "3.13" and extra == "all-extras"
Requires-Dist: matplotlib>=3.3.2; extra == "all-extras"
Requires-Dist: ngboost<0.6.0; python_version < "3.13" and extra == "all-extras"
Requires-Dist: polars<1.37.0; extra == "all-extras"
Requires-Dist: pymc; python_version < "3.13" and extra == "all-extras"
Requires-Dist: statsmodels>=0.12.1; extra == "all-extras"
Provides-Extra: dev
Requires-Dist: backoff; extra == "dev"
Requires-Dist: httpx; extra == "dev"
Requires-Dist: pre-commit; extra == "dev"
Requires-Dist: pytest; extra == "dev"
Requires-Dist: pytest-cov; extra == "dev"
Requires-Dist: pytest-randomly; extra == "dev"
Requires-Dist: pytest-timeout; extra == "dev"
Requires-Dist: pytest-xdist; extra == "dev"
Requires-Dist: wheel; extra == "dev"
Provides-Extra: binder
Requires-Dist: jupyter; extra == "binder"
Provides-Extra: docs
Requires-Dist: jupyter; extra == "docs"
Requires-Dist: myst-parser; extra == "docs"
Requires-Dist: nbsphinx>=0.8.6; extra == "docs"
Requires-Dist: numpydoc; extra == "docs"
Requires-Dist: pydata-sphinx-theme; extra == "docs"
Requires-Dist: sphinx!=7.2.0,<9.0.0; extra == "docs"
Requires-Dist: sphinx-design<0.7.0; extra == "docs"
Requires-Dist: sphinx-issues<6.0.0; extra == "docs"
Requires-Dist: sphinx-gallery<0.20.0; extra == "docs"
Requires-Dist: sphinx-panels; extra == "docs"
Requires-Dist: tabulate; extra == "docs"
Dynamic: license-file
